{
	"defaults": {
		"type": "cube",
		"color": "#00ccff",
		"opacity": 1.0,
		"start": 0.1,
		"duration": 2.0,
		"animation": "Elastic.InOut",
		"height": 1000
	},


	"objects": [

		{ "color": "#aaaaaa", "x": 0, "y": 0, "start": 0.1, "duration": 1},
		{ "color": "#aaaaaa", "x": 7, "y": 0, "start": 0.1, "duration": 1},
		{ "color": "#aaaaaa", "x": 0, "y": 7, "start": 0.1, "duration": 1},
		{ "color": "#aaaaaa", "x": 7, "y": 7, "start": 0.1, "duration": 1},

		{ "color": "#777777", "x": 1, "y": 1, "start": 3.1, "duration": 1},
		{ "color": "#777777", "x": 6, "y": 1, "start": 3.1, "duration": 1},
		{ "color": "#777777", "x": 1, "y": 6, "start": 3.1, "duration": 1},
		{ "color": "#777777", "x": 6, "y": 6, "start": 3.1, "duration": 1},

		{ "color": "#00ff00", "x": 2, "y": 2, "start": 6.1, "duration": 1},
		{ "color": "#00ff00", "x": 5, "y": 2, "start": 6.1, "duration": 1},
		{ "color": "#00ff00", "x": 2, "y": 5, "start": 6.1, "duration": 1},
		{ "color": "#00ff00", "x": 5, "y": 5, "start": 6.1, "duration": 1},

		{ "color": "#333333", "x": 3, "y": 3, "start": 6.1, "duration": 1},
		{ "color": "#333333", "x": 4, "y": 3, "start": 6.1, "duration": 1},
		{ "color": "#333333", "x": 3, "y": 4, "start": 6.1, "duration": 1},
		{ "color": "#333333", "x": 4, "y": 4, "start": 6.1, "duration": 1},

		{ "color": "#000000", "x": 3.5, "y": 3.5, "height": 300, "start": 0.1, "duration": 4}

	]
}